[{"id":"53567875191","latitude":"52.078266","longitude":"4.323055","country":{"_content":"Gemeente Den Haag"}},{"id":"53571278760","latitude":"52.083404","longitude":"4.309837","country":{"_content":"Gemeente Den Haag"}},{"id":"53567994673","latitude":"52.089902","longitude":"4.280440","country":{"_content":"Gemeente Den Haag"}},{"id":"53566107844","latitude":"52.081150","longitude":"4.313957","country":{"_content":"Gemeente Den Haag"}},{"id":"53565813364","latitude":"52.085755","longitude":"4.319894","country":{"_content":"Gemeente Den Haag"}},{"id":"53564405397","latitude":"52.079457","longitude":"4.312365","country":{"_content":"Gemeente Den Haag"}},{"id":"53565486219","latitude":"52.054911","longitude":"4.309387","country":{"_content":"Gemeente Den Haag"}},{"id":"53565002466","latitude":"52.093847","longitude":"4.297177","country":{"_content":"Gemeente Den Haag"}},{"id":"53561202277","latitude":"52.079811","longitude":"4.319878","country":{"_content":"Gemeente Den Haag"}},{"id":"53562663826","latitude":"52.077786","longitude":"4.308719","country":{"_content":"Gemeente Den Haag"}},{"id":"53556290062","latitude":"52.065661","longitude":"4.344269","country":{"_content":"Gemeente Den Haag"}},{"id":"53551453293","latitude":"52.078253","longitude":"4.299058","country":{"_content":"Gemeente Den Haag"}},{"id":"53550563694","latitude":"52.080258","longitude":"4.314261","country":{"_content":"Gemeente Den Haag"}},{"id":"53549787335","latitude":"52.077751","longitude":"4.316920","country":{"_content":"Gemeente Den Haag"}},{"id":"53548841363","latitude":"52.079804","longitude":"4.309269","country":{"_content":"Gemeente Den Haag"}},{"id":"53534920914","latitude":"52.077343","longitude":"4.318217","country":{"_content":"Gemeente Den Haag"}},{"id":"53528982668","latitude":"52.078041","longitude":"4.314017","country":{"_content":"Gemeente Den Haag"}},{"id":"53525729087","latitude":"52.084701","longitude":"4.314343","country":{"_content":"Gemeente Den Haag"}},{"id":"53526128466","latitude":"52.079487","longitude":"4.310864","country":{"_content":"Gemeente Den Haag"}},{"id":"53525085094","latitude":"52.078088","longitude":"4.311741","country":{"_content":"Gemeente Den Haag"}},{"id":"53515223052","latitude":"52.083000","longitude":"4.313151","country":{"_content":"Gemeente Den Haag"}},{"id":"53514108402","latitude":"52.079670","longitude":"4.313378","country":{"_content":"Gemeente Den Haag"}},{"id":"53513848587","latitude":"52.079934","longitude":"4.313828","country":{"_content":"Gemeente Den Haag"}},{"id":"53514076220","latitude":"52.086901","longitude":"4.297306","country":{"_content":"Gemeente Den Haag"}},{"id":"53513301270","latitude":"52.082168","longitude":"4.314738","country":{"_content":"Gemeente Den Haag"}},{"id":"53509936381","latitude":"52.083461","longitude":"4.314215","country":{"_content":"Gemeente Den Haag"}},{"id":"53511518388","latitude":"52.077376","longitude":"4.306554","country":{"_content":"Gemeente Den Haag"}},{"id":"53509502043","latitude":"52.081354","longitude":"4.307187","country":{"_content":"Gemeente Den Haag"}},{"id":"53507926533","latitude":"52.090388","longitude":"4.302842","country":{"_content":"Gemeente Den Haag"}},{"id":"53501110243","latitude":"52.073848","longitude":"4.317219","country":{"_content":"Gemeente Den Haag"}},{"id":"53493483565","latitude":"52.068475","longitude":"4.346858","country":{"_content":"Gemeente Den Haag"}},{"id":"53490420497","latitude":"52.080174","longitude":"4.318504","country":{"_content":"Gemeente Den Haag"}},{"id":"53491227311","latitude":"52.075140","longitude":"4.319697","country":{"_content":"Gemeente Den Haag"}},{"id":"53484737368","latitude":"52.081147","longitude":"4.312777","country":{"_content":"Gemeente Den Haag"}},{"id":"53477009627","latitude":"52.077456","longitude":"4.307391","country":{"_content":"Gemeente Den Haag"}},{"id":"53470605790","latitude":"52.079064","longitude":"4.322690","country":{"_content":"Gemeente Den Haag"}},{"id":"53463725899","latitude":"52.090529","longitude":"4.279561","country":{"_content":"Gemeente Den Haag"}},{"id":"53461857091","latitude":"52.076339","longitude":"4.275680","country":{"_content":"Gemeente Den Haag"}}]